testr_recipe
