Metadata-Version: 1.0
Name: testr-recipe
Version: 0.3
Summary: buildout recipe to create scripts to run testrepository.
Home-page: https://launchpad.net/testr_recipe
Author: James Westby
Author-email: james.westby@linaro.org
License: ZPL
Keywords: testing testrepository testr buildout recipe
Platform: UNKNOWN
Classifier: Development Status :: 3 - Alpha
Classifier: Environment :: Plugins
Classifier: Framework :: Buildout
Classifier: Intended Audience :: Developers
Classifier: License :: OSI Approved :: Zope Public License
Classifier: Programming Language :: Python
Classifier: Topic :: Software Development :: Testing
